lektor_inlinetags.py
lektor_inlinetags-0.9.2.dist-info/LICENSE
lektor_inlinetags-0.9.2.dist-info/METADATA
lektor_inlinetags-0.9.2.dist-info/WHEEL
lektor_inlinetags-0.9.2.dist-info/entry_points.txt
lektor_inlinetags-0.9.2.dist-info/top_level.txt
lektor_inlinetags-0.9.2.dist-info/RECORD
