Metadata-Version: 2.1
Name: lektor-inlinetags
Version: 0.9.2
Summary: Auto-detect and reference tags inside written text.
Home-page: https://github.com/relikd/lektor-inlinetags-plugin
Author: relikd
License: MIT
Keywords: lektor,plugin,blog,tags,tagging
Platform: UNKNOWN
Classifier: Environment :: Web Environment
Classifier: Environment :: Plugins
Classifier: Framework :: Lektor
Classifier: License :: OSI Approved :: MIT License
Classifier: Operating System :: OS Independent
Classifier: Programming Language :: Python
Classifier: Programming Language :: Python :: 3
Classifier: Programming Language :: Python :: 3 :: Only
Classifier: Programming Language :: Python :: 3.6
Classifier: Programming Language :: Python :: 3.7
Classifier: Programming Language :: Python :: 3.8
Requires-Python: >=3.6
Requires-Dist: lektor-groupby (==0.9.8)
